HypixelPlayerApi/__init__.py
HypixelPlayerApi/plr.py
HypixelPlayerApi-1.1.2.dist-info/LICENSE
HypixelPlayerApi-1.1.2.dist-info/METADATA
HypixelPlayerApi-1.1.2.dist-info/WHEEL
HypixelPlayerApi-1.1.2.dist-info/top_level.txt
HypixelPlayerApi-1.1.2.dist-info/RECORD
