Metadata-Version: 2.1
Name: HypixelPlayerApi
Version: 1.1.2
Summary: A package that you can use to get the data of a player in hypixel, and hypixel skyblock.
Author-email: Keshav Verma <vkeshav300@gmail.com>
Maintainer-email: Keshav Verma <vkeshav300@gmail.com>
License: MIT License        
Project-URL: Homepage, https://github.com/vkeshav300/PlayerApiContact/
Project-URL: Bug Tracker, https://github.com/vkeshav300/PlayerApiContact/issues/
Project-URL: Releases, https://github.com/vkeshav300/PlayerApiContact/releases/
Classifier: Programming Language :: Python :: 3
Classifier: License :: OSI Approved :: MIT License
Classifier: Operating System :: OS Independent
Classifier: Natural Language :: English
Classifier: Development Status :: 7 - Inactive
Requires-Python: >=3.9.13
License-File: LICENSE
